COPYING
MANIFEST.in
README
bugspots.py
setup.py
bugspots.egg-info/PKG-INFO
bugspots.egg-info/SOURCES.txt
bugspots.egg-info/dependency_links.txt
bugspots.egg-info/requires.txt
bugspots.egg-info/top_level.txt